conformity_migration/__init__.py
conformity_migration/cloud_accounts.py
conformity_migration/conformity_api.py
conformity_migration/models.py
conformity_migration/typing.py
conformity_migration_tool/__init__.py
conformity_migration_tool/aws_cli.py
conformity_migration_tool/cli.py
conformity_migration_tool/config.yml
conformity_migration_tool/di.py
conformity_migration_tool/logger.py
conformity_migration_tool/utils.py
conformity_migration_tool-0.13.0.dist-info/LICENSE
conformity_migration_tool-0.13.0.dist-info/METADATA
conformity_migration_tool-0.13.0.dist-info/WHEEL
conformity_migration_tool-0.13.0.dist-info/entry_points.txt
conformity_migration_tool-0.13.0.dist-info/top_level.txt
conformity_migration_tool-0.13.0.dist-info/RECORD
