Metadata-Version: 2.1
Name: conformity-migration-tool
Version: 0.13.0
Summary: Migrates your visiblity information in cloudconformity.com to cloudone.trendmicro.com
Home-page: https://github.com/atiradocc/conformity-migration-tool
Author: Ronald Bautista
License: MIT
Project-URL: Source Code, https://github.com/atiradocc/conformity-migration-tool
Classifier: Development Status :: 3 - Alpha
Classifier: Environment :: Console
Classifier: Intended Audience :: Developers
Classifier: Intended Audience :: Information Technology
Classifier: Intended Audience :: System Administrators
Classifier: License :: OSI Approved :: MIT License
Classifier: Operating System :: OS Independent
Classifier: Programming Language :: Python
Classifier: Programming Language :: Python :: 3.7
Classifier: Programming Language :: Python :: 3.8
Classifier: Programming Language :: Python :: 3.9
Requires-Python: >=3.7
License-File: LICENSE
Requires-Dist: typing-extensions (>=4.0.0)
Requires-Dist: requests (<3.0.0,>=2.0.0)
Requires-Dist: PyYAML (<7.0,>=6.0)
Requires-Dist: deepdiff (<6.0.0,>=5.7.0)
Requires-Dist: backoff (>=1.11.1)
Requires-Dist: vcrpy (<5.0.0,>=4.0.0)
Requires-Dist: PyInquirer (<2.0.0,>=1.0.3)
Requires-Dist: click (<9.0.0,>=8.0.0)
Requires-Dist: boto3 (<2.0.0,>=1.0.0)
Requires-Dist: boto3-stubs[cloudformation]
Requires-Dist: importlib-metadata ; python_version < "3.8"
